realfast/__init__.py
realfast/cli.py
realfast/controllers.py
realfast/elastic.py
realfast/heuristics.py
realfast/pipeline.py
realfast/sdm_builder.py
realfast/xsd/SdmBuilderMessage.xsd
realfast-3.3.1.data/data/conf/realfast.yml
realfast-3.3.1.data/data/conf/redis_aoc.conf
realfast-3.3.1.data/data/conf/redis_cbe.conf
realfast-3.3.1.data/data/conf/rtpipe_cbe.conf
realfast-3.3.1.data/data/conf/supervisord_aoc.conf
realfast-3.3.1.data/data/conf/supervisord_cbe.conf
realfast-3.3.1.dist-info/METADATA
realfast-3.3.1.dist-info/RECORD
realfast-3.3.1.dist-info/WHEEL
realfast-3.3.1.dist-info/entry_points.txt
realfast-3.3.1.dist-info/top_level.txt
